shortpaw/__init__.py
shortpaw/__main__.py
ShortPaw-0.0.1.dist-info/LICENSE
ShortPaw-0.0.1.dist-info/METADATA
ShortPaw-0.0.1.dist-info/WHEEL
ShortPaw-0.0.1.dist-info/entry_points.txt
ShortPaw-0.0.1.dist-info/top_level.txt
ShortPaw-0.0.1.dist-info/RECORD
